venv_py/__init__.py
venv_py/env_manager.py
venv_py-0.1.1.dist-info/METADATA
venv_py-0.1.1.dist-info/WHEEL
venv_py-0.1.1.dist-info/licenses/LICENSE
venv_py-0.1.1.dist-info/RECORD
