Metadata-Version: 2.4
Name: venv_py
Version: 0.1.1
Summary: virtual environment lifecycle manager
Author: r4d4m4n71s
License-File: LICENSE
Requires-Python: >=3.8
Provides-Extra: dev
Requires-Dist: black>=23.0; extra == 'dev'
Requires-Dist: mypy>=1.0; extra == 'dev'
Requires-Dist: pytest; extra == 'dev'
Requires-Dist: ruff>=0.1.0; extra == 'dev'
